poker_reinforcement_learning/__init__.py
poker_reinforcement_learning/client.py
poker_reinforcement_learning/deck.py
poker_reinforcement_learning/dummy_agent.py
poker_reinforcement_learning/limp_agent.py
poker_reinforcement_learning/poker_host.py
poker_reinforcement_learning/server.py
poker_reinforcement_learning-0.1.9.dist-info/LICENSE.txt
poker_reinforcement_learning-0.1.9.dist-info/METADATA
poker_reinforcement_learning-0.1.9.dist-info/WHEEL
poker_reinforcement_learning-0.1.9.dist-info/top_level.txt
poker_reinforcement_learning-0.1.9.dist-info/RECORD
