Metadata-Version: 2.2
Name: poker_reinforcement_learning
Version: 0.1.9
Summary: Testbed for Reinforcement Learning in Poker. Implemented with Client/Socket technology.
Author-email: Sai Coumar <sai.c.coumar1@gmail.com>
Maintainer-email: Sai Coumar <sai.c.coumar1@gmail.com>
License:                     GNU GENERAL PUBLIC LICENSE
Project-URL: Homepage, https://github.com/saiccoumar/Poker
Project-URL: Bug Reports, https://github.com/saiccoumar/Poker/issues
Project-URL: Source, https://github.com/saiccoumar/Poker
Keywords: poker,testbed,reinforcement learning,python,server
Classifier: Development Status :: 4 - Beta
Classifier: Intended Audience :: Developers
Classifier: License :: OSI Approved :: GNU General Public License v3 (GPLv3)
Classifier: Programming Language :: Python :: 3
Classifier: Programming Language :: Python :: 3 :: Only
Requires-Python: >=3.11
License-File: LICENSE.txt
Provides-Extra: test
Requires-Dist: unittest; extra == "test"
